bucket_utils/__init__.py
bucket_utils/exceptions.py
bucket_utils/google.py
bucket_utils/interface.py
bucket_utils/local.py
bucket_utils/resumable_upload_session.py
spand-0.1.3.dist-info/LICENSE
spand-0.1.3.dist-info/METADATA
spand-0.1.3.dist-info/WHEEL
spand-0.1.3.dist-info/RECORD
