Metadata-Version: 2.1
Name: spand
Version: 0.1.3
Summary: Utility classes for interacting with cloud buckets
Author: Magnus Hansen
Author-email: maha@mapspeople.com
Requires-Python: >=3.10,<4.0
Classifier: Programming Language :: Python :: 3
Classifier: Programming Language :: Python :: 3.10
Classifier: Programming Language :: Python :: 3.11
Classifier: Programming Language :: Python :: 3.12
Requires-Dist: crc32c (>=2.3.0)
Requires-Dist: google-cloud-storage (>=2.0.0)
Requires-Dist: pytz (>=2024.1)
